pandas_nosql/__init__.py
pandas_nosql-1.2.0.dist-info/LICENSE
pandas_nosql-1.2.0.dist-info/METADATA
pandas_nosql-1.2.0.dist-info/WHEEL
pandas_nosql-1.2.0.dist-info/top_level.txt
pandas_nosql-1.2.0.dist-info/RECORD
