Metadata-Version: 2.1
Name: pandas-nosql
Version: 1.2.0
Summary: A Module to add read and write capabilities to pandas for several nosql databases
Home-page: https://bitbucket.org/blacklotus231/pandas-nosql
Author: James Baker Jr
License: Apache License 2.0
Keywords: pandas,nosql,mongo,mongodb,elasticsearch,redis,cassandra,apache-cassandra
Classifier: License :: OSI Approved :: Apache Software License
Classifier: Operating System :: OS Independent
Classifier: Programming Language :: Python :: 3
Classifier: Programming Language :: Python :: 3.10
Requires-Python: >=3.10
License-File: LICENSE
Requires-Dist: pandas (>=1.4.4)
